fish_audio_preprocess/__init__.py
fish_audio_preprocess/cli/__main__.py
fish_audio_preprocess/cli/convert_to_wav.py
fish_audio_preprocess/cli/frequency.py
fish_audio_preprocess/cli/length.py
fish_audio_preprocess/cli/loudness_norm.py
fish_audio_preprocess/cli/merge_short.py
fish_audio_preprocess/cli/resample.py
fish_audio_preprocess/cli/separate_audio.py
fish_audio_preprocess/cli/slice_audio.py
fish_audio_preprocess/cli/transcribe.py
fish_audio_preprocess/utils/file.py
fish_audio_preprocess/utils/loudness_norm.py
fish_audio_preprocess/utils/separate_audio.py
fish_audio_preprocess/utils/slice_audio.py
fish_audio_preprocess/utils/slice_audio_v2.py
fish_audio_preprocess/utils/transcribe.py
fish_audio_preprocess-0.2.8.dist-info/LICENSE
fish_audio_preprocess-0.2.8.dist-info/METADATA
fish_audio_preprocess-0.2.8.dist-info/WHEEL
fish_audio_preprocess-0.2.8.dist-info/entry_points.txt
fish_audio_preprocess-0.2.8.dist-info/top_level.txt
fish_audio_preprocess-0.2.8.dist-info/RECORD
