Metadata-Version: 2.1
Name: fish-audio-preprocess
Version: 0.2.8
Summary: Preprocess audio data
Author-email: Lengyue <lengyue@lengyue.me>
License: Apache
Requires-Python: >=3.9
License-File: LICENSE
Requires-Dist: tqdm >=4.64.1
Requires-Dist: demucs >=4.0.0
Requires-Dist: loguru >=0.6.0
Requires-Dist: pyloudnorm >=0.1.1
Requires-Dist: matplotlib >=3.6.2
Requires-Dist: librosa >=0.9.0
Requires-Dist: richuru >=0.1.1
Requires-Dist: praat-parselmouth >=0.4.3
Requires-Dist: click >=8.0.0
Requires-Dist: openai-whisper
